biglist/__init__.py
biglist/_biglist.py
biglist/_parquet.py
biglist/_util.py
biglist/py.typed
biglist-0.9.6.dist-info/LICENSE
biglist-0.9.6.dist-info/WHEEL
biglist-0.9.6.dist-info/METADATA
biglist-0.9.6.dist-info/RECORD
