Metadata-Version: 2.3
Name: biglist
Version: 0.9.6
Summary: The package `biglist <https://github.com/zpz/biglist>`_ provides persisted, out-of-memory Python data structures
Author-email: Zepu Zhang <zepu.zhang@gmail.com>
Requires-Python: >=3.10
Classifier: Intended Audience :: Developers
Classifier: Programming Language :: Python :: 3
Classifier: Topic :: Software Development :: Libraries :: Python Modules
Requires-Dist: upathlib >= 0.9.3
Requires-Dist: deprecation
Requires-Dist: pyarrow >= 12.0.1
Requires-Dist: typing-extensions
Requires-Dist: zstandard
Requires-Dist: sphinx ; extra == "doc"
Requires-Dist: numpydoc ; extra == "doc"
Requires-Dist: pydata-sphinx-theme ; extra == "doc"
Requires-Dist: cloudly[gcp] >= 0.0.3 ; extra == "gcs"
Requires-Dist: upathlib[gcs] >= 0.9.8 ; extra == "gcs"
Requires-Dist: boltons ; extra == "test"
Requires-Dist: pytest-asyncio ; extra == "test"
Project-URL: Source, https://github.com/zpz/biglist
Provides-Extra: doc
Provides-Extra: gcs
Provides-Extra: test
